istatcelldata/__init__.py
istatcelldata/census1991/__init__.py
istatcelldata/census1991/download.py
istatcelldata/census1991/process.py
istatcelldata/census1991/utils.py
istatcelldata/census2001/__init__.py
istatcelldata/census2001/download.py
istatcelldata/census2011/__init__.py
istatcelldata/census2011/download.py
istatcelldata/census2021/__init__.py
istatcelldata/census2021/download.py
istatcelldata/census2021/utils.py
istatcelldata/config.py
istatcelldata/data.py
istatcelldata/download.py
istatcelldata/executor/__init__.py
istatcelldata/executor/download.py
istatcelldata/executor/preprocess.py
istatcelldata/executor/process.py
istatcelldata/geodata.py
istatcelldata/logger_config.py
istatcelldata/utils.py
istatcelldata-1.3.0.dist-info/LICENSE
istatcelldata-1.3.0.dist-info/METADATA
istatcelldata-1.3.0.dist-info/WHEEL
istatcelldata-1.3.0.dist-info/RECORD
